function_notifier/__init__.py
function_notifier/send_notification.py
function_notifier-1.0.1.dist-info/LICENSE.txt
function_notifier-1.0.1.dist-info/METADATA
function_notifier-1.0.1.dist-info/WHEEL
function_notifier-1.0.1.dist-info/top_level.txt
function_notifier-1.0.1.dist-info/RECORD
