Metadata-Version: 2.1
Name: function_notifier
Version: 1.0.1
Summary: This package contains the notify decorator, used to notify users when the wrapped function has finished execution.
Home-page: https://github.com/LewisDean22/function_notifier
Author: Lewis Dean
Classifier: Programming Language :: Python :: 3
Classifier: License :: OSI Approved :: MIT License
Classifier: Operating System :: OS Independent
Requires-Python: >=3.11
License-File: LICENSE.txt
Requires-Dist: plyer >=2.1.0
